callback/__init__.py
callback/callback.py
callback_factory-0.0.3.dist-info/LICENSE
callback_factory-0.0.3.dist-info/METADATA
callback_factory-0.0.3.dist-info/WHEEL
callback_factory-0.0.3.dist-info/top_level.txt
callback_factory-0.0.3.dist-info/RECORD
