Metadata-Version: 2.1
Name: callback-factory
Version: 0.0.3
Summary: A simple Python library for producing parameterized         and flexible callbacks that can be overriden during execution
Home-page: https://github.com/chrisK824/callback
Author: Chris Karvouniaris
Author-email: christos.karvouniaris247@gmail.com
Classifier: Programming Language :: Python :: 3
Classifier: License :: OSI Approved :: MIT License
Classifier: Operating System :: OS Independent
Requires-Python: >=3.5
License-File: LICENSE
